.dockerignore
.gitlab-ci.yml
.gitmodules
.mailmap
AUTHORS
CONTRIBUTING.md
ChangeLog
LICENSE
Makefile
README.md
ansible.cfg
bootstrap
clouds.yml.example
conftest.py
enough-community-playbook.yml
hosts-base.yml
id_rsa
id_rsa.pub
private-key.yml.example
requirements-dev.in
requirements-dev.txt
requirements.in
requirements.txt
setup.cfg
setup.py
tox.ini
certs/0a3654cf.0
certs/5a7a72df.0
certs/fakeleintermediatex1.pem
certs/fakelerootx1.pem
certs/isrgrootx1.pem
certs/lets-encrypt-x3-cross-signed.pem
certs/letsencryptauthorityx3.pem
cookiecutter/cookiecutter.json
cookiecutter/hooks/post_gen_project.sh
cookiecutter/{{cookiecutter.scenario_name}}/molecule.yml
cookiecutter/{{cookiecutter.scenario_name}}/playbook.yml
cookiecutter/{{cookiecutter.scenario_name}}/{{cookiecutter.scenario_name}}-playbook.yml
cookiecutter/{{cookiecutter.scenario_name}}/roles/{{cookiecutter.role_name}}/tasks/main.yml
docs/Makefile
docs/ansible.rst
docs/authorized_keys.rst
docs/backup.rst
docs/bind.rst
docs/conf.py
docs/contribute.rst
docs/documentation.rst
docs/enough.rst
docs/extending.rst
docs/funding.rst
docs/gitlab.rst
docs/ids.rst
docs/index.rst
docs/infrastructure.rst
docs/mattermost.rst
docs/monitoring_architecture.rst
docs/monitoring_howto.rst
docs/postfix.rst
docs/team.rst
docs/weblate.rst
enough/__init__.py
enough/cmd.py
enough/version.py
enough.egg-info/PKG-INFO
enough.egg-info/SOURCES.txt
enough.egg-info/dependency_links.txt
enough.egg-info/entry_points.txt
enough.egg-info/not-zip-safe
enough.egg-info/pbr.json
enough.egg-info/requires.txt
enough.egg-info/top_level.txt
enough/cli/__init__.py
enough/cli/create.py
enough/common/__init__.py
enough/common/docker.py
enough/common/retry.py
enough/common/data/base.dockerfile
enough/internal/__init__.py
enough/internal/cmd.py
enough/internal/cli/__init__.py
enough/internal/cli/docker.py
enough/internal/cli/install.py
enough/internal/data/enough.dockerfile
enough/internal/data/install.sh
inventories/common/02-all.yml
inventories/common/all.yml
inventories/common/firewall.yml
inventories/common/group_vars/all/letsencrypt_nginx_staging.yml
inventories/common/group_vars/all/production_domain.yml
inventories/common/host_vars/chat-host/chat.yml
