Metadata-Version: 1.1
Name: enough
Version: 1.0.0
Summary: Helping journalists and human rights defefenders to communicate securely and privately
Home-page: https://lab.enough.community/main/infrastructure
Author: Enough Community
Author-email: contact@enough.community
License: AGPLv3+
Project-URL: Bug Tracker, https://lab.enough.community/main/infrastructure/issues
Project-URL: Documentation, https://enough-community.readthedocs.io/
Project-URL: Source Code, https://lab.enough.community/main/infrastructure
Keywords: setup
Platform: UNKNOWN
Classifier: Development Status :: 4 - Beta
Classifier: Environment :: Console
Classifier: Intended Audience :: Developers
Classifier: Intended Audience :: Information Technology
Classifier: License :: OSI Approved :: GNU Affero General Public License v3 or later (AGPLv3+)
Classifier: Operating System :: OS Independent
Classifier: Programming Language :: Python
